youtubeenhanced/__init__.py
youtubeenhanced/enums/__init__.py
youtubeenhanced/experimental/__init__.py
youtubeenhanced/experimental/uploader.py
youtubeenhanced/objects/__init__.py
youtubeenhanced/objects/youtube.py
youtubeenhanced/objects/youtube_video.py
youtubeenhanced/objects/youtube_video_subtitles.py
youtubeenhanced/utils/__init__.py
youtubeenhanced/utils/youtube_api.py
youtubeenhanced-0.0.37.dist-info/LICENSE
youtubeenhanced-0.0.37.dist-info/METADATA
youtubeenhanced-0.0.37.dist-info/WHEEL
youtubeenhanced-0.0.37.dist-info/top_level.txt
youtubeenhanced-0.0.37.dist-info/RECORD
