Metadata-Version: 2.1
Name: youtubeenhanced
Version: 0.0.37
Summary: Youtube Enhanced simplifies the interaction with Youtube videos.
Home-page: UNKNOWN
Author: Daniel Alcalá
Author-email: <danielalcalavalera@gmail.com>
License: UNKNOWN
Keywords: youtube enhanced,youtube downloader
Platform: UNKNOWN
Classifier: Development Status :: 3 - Alpha
Classifier: Intended Audience :: Education
Classifier: Programming Language :: Python :: 2
Classifier: Programming Language :: Python :: 3
Classifier: Operating System :: MacOS :: MacOS X
Classifier: Operating System :: Microsoft :: Windows
Requires-Dist: yt-dlp
Requires-Dist: yta-google-api
Requires-Dist: yta-general-utils
